memmachine/__init__.py
memmachine/common/__init__.py
memmachine/common/builder.py
memmachine/common/data_types.py
memmachine/common/embedder/__init__.py
memmachine/common/embedder/amazon_bedrock_embedder.py
memmachine/common/embedder/data_types.py
memmachine/common/embedder/embedder.py
memmachine/common/embedder/embedder_builder.py
memmachine/common/embedder/openai_embedder.py
memmachine/common/embedder/sentence_transformer_embedder.py
memmachine/common/language_model/__init__.py
memmachine/common/language_model/amazon_bedrock_language_model.py
memmachine/common/language_model/language_model.py
memmachine/common/language_model/language_model_builder.py
memmachine/common/language_model/openai_compatible_language_model.py
memmachine/common/language_model/openai_language_model.py
memmachine/common/metrics_factory/__init__.py
memmachine/common/metrics_factory/metrics_factory.py
memmachine/common/metrics_factory/metrics_factory_builder.py
memmachine/common/metrics_factory/prometheus_metrics_factory.py
memmachine/common/reranker/__init__.py
memmachine/common/reranker/amazon_bedrock_reranker.py
memmachine/common/reranker/bm25_reranker.py
memmachine/common/reranker/cross_encoder_reranker.py
memmachine/common/reranker/embedder_reranker.py
memmachine/common/reranker/identity_reranker.py
memmachine/common/reranker/reranker.py
memmachine/common/reranker/reranker_builder.py
memmachine/common/reranker/rrf_hybrid_reranker.py
memmachine/common/resource_initializer.py
memmachine/common/utils.py
memmachine/common/vector_graph_store/__init__.py
memmachine/common/vector_graph_store/data_types.py
memmachine/common/vector_graph_store/neo4j_vector_graph_store.py
memmachine/common/vector_graph_store/vector_graph_store.py
memmachine/common/vector_graph_store/vector_graph_store_builder.py
memmachine/episodic_memory/__init__.py
memmachine/episodic_memory/data_types.py
memmachine/episodic_memory/declarative_memory/__init__.py
memmachine/episodic_memory/declarative_memory/data_types.py
memmachine-0.1.9.dist-info/licenses/LICENSE
memmachine-0.1.9.dist-info/WHEEL
memmachine-0.1.9.dist-info/entry_points.txt
memmachine-0.1.9.dist-info/METADATA
memmachine-0.1.9.dist-info/RECORD
