Metadata-Version: 2.4
Name: memmachine
Version: 0.1.9
Summary: MemMachine is an open-source memory layer for AI agents, giving your creations short-term, long-term, and personalization memory, enabling them to learn, adapt, and remember.
Keywords: memmachine
Author: MemMachine
Author-email: MemMachine <noreply@memmachine.ai>
License-Expression: Apache-2.0
License-File: LICENSE
Classifier: Programming Language :: Python :: 3
Classifier: Operating System :: OS Independent
Requires-Dist: asyncpg>=0.30.0
Requires-Dist: boto3>=1.40.40
Requires-Dist: dotenv>=0.9.9
Requires-Dist: fastapi>=0.116.1
Requires-Dist: fastmcp>=2.12.0
Requires-Dist: langchain-aws>=0.2.33
Requires-Dist: neo4j>=5.28.2
Requires-Dist: nltk>=3.9.1
Requires-Dist: openai>=1.104.2
Requires-Dist: pgvector>=0.4.1
Requires-Dist: prometheus-client>=0.22.1
Requires-Dist: pydantic>=2.11.7
Requires-Dist: pyyaml>=6.0.2
Requires-Dist: rank-bm25>=0.2.2
Requires-Dist: sqlalchemy>=2.0.43
Requires-Dist: uvicorn>=0.35.0
Requires-Dist: sentence-transformers>=5.1.0 ; extra == 'gpu'
Requires-Python: >=3.12
Project-URL: Homepage, https://github.com/MemMachine/MemMachine
Project-URL: Issues, https://github.com/MemMachine/MemMachine/issues
Provides-Extra: gpu
